{
  "fecha": "2026-03-24",
  "hora": "09:49",
  "periodo": "Primer Reporte — Planeación de despachos nacionales",
  "total_novedades": 0,
  "resumen": {
    "alto": 0,
    "medio": 0,
    "bajo": 0
  },
  "novedades": [],
  "errores_scraping": [
    {
      "fuente": "INVÍAS",
      "error": "Message: \nStacktrace:\n#0 0x561c87fdab6a <unknown>\n#1 0x561c879eda32 <unknown>\n#2 0x561c87a42d66 <unknown>\n#3 0x561c87a42fa1 <unknown>\n#4 0x561c87a8e144 <unknown>\n#5 0x561c87a8b369 <unknown>\n#6 0x561c87a34c0f <unknown>\n#7 0x561c87a359d1 <unknown>\n#8 0x561c87f9f6b9 <unknown>\n#9 0x561c87fa25c1 <unknown>\n#10 0x561c87f8be29 <unknown>\n#11 0x561c87fa317e <unknown>\n#12 0x561c87f724b0 <unknown>\n#13 0x561c87fc7578 <unknown>\n#14 0x561c87fc774b <unknown>\n#15 0x561c87fd91a3 <unknown>\n#16 0x7fb48ca9caa4 <unknown>\n#17 0x7fb48cb29c6c <unknown>\n",
      "timestamp": "2026-03-24T09:45:13.246622"
    },
    {
      "fuente": "ANI",
      "error": "Message: timeout: Timed out receiving message from renderer: 29.649\n  (Session info: chrome=145.0.7632.159)\nStacktrace:\n#0 0x5646a801ab6a <unknown>\n#1 0x5646a7a2da32 <unknown>\n#2 0x5646a7a15007 <unknown>\n#3 0x5646a7a14c16 <unknown>\n#4 0x5646a7a12731 <unknown>\n#5 0x5646a7a130bf <unknown>\n#6 0x5646a7a22560 <unknown>\n#7 0x5646a7a3c707 <unknown>\n#8 0x5646a7a438db <unknown>\n#9 0x5646a7a13829 <unknown>\n#10 0x5646a7a3c49c <unknown>\n#11 0x5646a7acb6e1 <unknown>\n#12 0x5646a7a74c0f <unknown>\n#13 0x5646a7a759d1 <unknown>\n#14 0x5646a7fdf6b9 <unknown>\n#15 0x5646a7fe25c1 <unknown>\n#16 0x5646a7fcbe29 <unknown>\n#17 0x5646a7fe317e <unknown>\n#18 0x5646a7fb24b0 <unknown>\n#19 0x5646a8007578 <unknown>\n#20 0x5646a800774b <unknown>\n#21 0x5646a80191a3 <unknown>\n#22 0x7fa5bd89caa4 <unknown>\n#23 0x7fa5bd929c6c <unknown>\n",
      "timestamp": "2026-03-24T09:46:18.979821"
    },
    {
      "fuente": "Movilidad Bogotá",
      "error": "Message: \nStacktrace:\n#0 0x555bf72e3b6a <unknown>\n#1 0x555bf6cf6a32 <unknown>\n#2 0x555bf6d4bd66 <unknown>\n#3 0x555bf6d4bfa1 <unknown>\n#4 0x555bf6d97144 <unknown>\n#5 0x555bf6d94369 <unknown>\n#6 0x555bf6d3dc0f <unknown>\n#7 0x555bf6d3e9d1 <unknown>\n#8 0x555bf72a86b9 <unknown>\n#9 0x555bf72ab5c1 <unknown>\n#10 0x555bf7294e29 <unknown>\n#11 0x555bf72ac17e <unknown>\n#12 0x555bf727b4b0 <unknown>\n#13 0x555bf72d0578 <unknown>\n#14 0x555bf72d074b <unknown>\n#15 0x555bf72e21a3 <unknown>\n#16 0x7fa15c89caa4 <unknown>\n#17 0x7fa15c929c6c <unknown>\n",
      "timestamp": "2026-03-24T09:48:21.876771"
    }
  ],
  "archivo_html": "Boletin_Vias_TCCondor_20260324_0949.html"
}